evative7enc/__init__.py
evative7enc/console.py
evative7enc/v1.py
evative7encrypter-1.2.1.dist-info/METADATA
evative7encrypter-1.2.1.dist-info/WHEEL
evative7encrypter-1.2.1.dist-info/entry_points.txt
evative7encrypter-1.2.1.dist-info/top_level.txt
evative7encrypter-1.2.1.dist-info/RECORD
