Metadata-Version: 2.4
Name: EvATive7Encrypter
Version: 1.2.1
Summary: Definition, specification, implementation and toolkit of EvATive7ENC
Author: EvATive7
Project-URL: Homepage, https://github.com/EvATive7/EvATive7Encrypter
Classifier: Programming Language :: Python :: 3
Classifier: Operating System :: OS Independent
Requires-Python: >=3.6
Provides-Extra: dev
Requires-Dist: black; extra == "dev"
Requires-Dist: isort; extra == "dev"
Requires-Dist: flake8; extra == "dev"
Requires-Dist: pytest; extra == "dev"
Requires-Dist: pre-commit; extra == "dev"
Requires-Dist: pytest-console-scripts; extra == "dev"
Requires-Dist: pytest-cov; extra == "dev"
Provides-Extra: build
Requires-Dist: build; extra == "build"
